kivy_garden/simpletablelayout/__init__.py
kivy_garden/simpletablelayout/_version.py
kivy_garden/simpletablelayout/tests/test_import.py
kivy_garden.simpletablelayout-0.1.dist-info/AUTHORS.txt
kivy_garden.simpletablelayout-0.1.dist-info/LICENSE
kivy_garden.simpletablelayout-0.1.dist-info/METADATA
kivy_garden.simpletablelayout-0.1.dist-info/WHEEL
kivy_garden.simpletablelayout-0.1.dist-info/top_level.txt
kivy_garden.simpletablelayout-0.1.dist-info/RECORD
