Metadata-Version: 2.1
Name: kivy-garden.simpletablelayout
Version: 0.1
Summary: Simple Table Layout – HTML table-like layout that supports rowspan and colspan, built into Kivy Garden.
Home-page: https://github.com/Tungsteno74/garden.simpletablelayout
Author: Kivy
Author-email: kivy@kivy.org
License: UNKNOWN
Project-URL: Bug Reports, https://github.com/Tungsteno74/garden.simpletablelayout/issues
Project-URL: Source, https://github.com/Tungsteno74/garden.simpletablelayout
Keywords: Kivy kivy-garden
Platform: UNKNOWN
Classifier: Development Status :: 4 - Beta
Classifier: Intended Audience :: Developers
Classifier: Topic :: Software Development :: Libraries
Classifier: License :: OSI Approved :: MIT License
Classifier: Programming Language :: Python :: 3.5
Classifier: Programming Language :: Python :: 3.6
Classifier: Programming Language :: Python :: 3.7
Classifier: Programming Language :: Python :: 3.8
License-File: LICENSE
License-File: AUTHORS.txt
Provides-Extra: ci
Requires-Dist: coveralls; extra == "ci"
Requires-Dist: pycodestyle; extra == "ci"
Provides-Extra: dev
Requires-Dist: pytest>=3.6; extra == "dev"
Requires-Dist: pytest-cov; extra == "dev"
Requires-Dist: pytest-asyncio; extra == "dev"
Requires-Dist: sphinx-rtd-theme; extra == "dev"
